LICENSE
MANIFEST.in
README.rst
distribute_setup.py
setup.py
gzipper/__init__.py
gzipper/version.py
hyde_gzipper.egg-info/PKG-INFO
hyde_gzipper.egg-info/SOURCES.txt
hyde_gzipper.egg-info/dependency_links.txt
hyde_gzipper.egg-info/top_level.txt
hyde_gzipper.egg-info/zip-safe