Metadata-Version: 1.1
Name: hyde-gzipper
Version: 1.0
Summary: Hyde plugin for gzipping files
Home-page: http://rczajka.pl/hyde-gzipper
Author: Radek Czajka
Author-email: rczajka@rczajka.pl
License: MIT
Platform: UNKNOWN
Classifier: Development Status :: 1 - Planning
Classifier: Environment :: Plugins
Classifier: Intended Audience :: Developers
Classifier: Intended Audience :: System Administrators
Classifier: License :: OSI Approved :: MIT License
Classifier: Programming Language :: Python
Classifier: Topic :: Internet :: WWW/HTTP :: Site Management
Requires: python (>= 2.7)
